LICENSE
MANIFEST.in
README.md
setup.py
libpythonprogoldani/__init__.py
libpythonprogoldani/github_api.py
libpythonprogoldani.egg-info/PKG-INFO
libpythonprogoldani.egg-info/SOURCES.txt
libpythonprogoldani.egg-info/dependency_links.txt
libpythonprogoldani.egg-info/not-zip-safe
libpythonprogoldani.egg-info/requires.txt
libpythonprogoldani.egg-info/top_level.txt
libpythonprogoldani/spam/__init__.py
libpythonprogoldani/spam/enviador_de_email.py
libpythonprogoldani/tests/__init__.py
libpythonprogoldani/tests/test_exemplo.py
libpythonprogoldani/tests/test_spam/__init__.py
libpythonprogoldani/tests/test_spam/test_enviador_de_email.py