Metadata-Version: 2.1
Name: libpythonprogoldani
Version: 0.3
Summary: Módulo para exemplificar construção de projetos Python no curso PyTools
Home-page: https://github.com/ggoldani/libpythonpro
Author: Gustavo Goldani
Author-email: tech.goldani@gmail.com
License: MIT
Platform: UNKNOWN
Classifier: Development Status :: 2 - Pre-Alpha
Classifier: Environment :: Console
Classifier: Intended Audience :: Developers
Classifier: License :: OSI Approved :: GNU Affero General Public License v3 or later (AGPLv3+)
Classifier: Operating System :: OS Independent
Classifier: Programming Language :: Python :: 3.9
Classifier: Framework :: Pytest
